sveve/__init__.py
sveve/client.py
Sveve-1.1.0.dist-info/LICENSE
Sveve-1.1.0.dist-info/METADATA
Sveve-1.1.0.dist-info/WHEEL
Sveve-1.1.0.dist-info/top_level.txt
Sveve-1.1.0.dist-info/RECORD
