Metadata-Version: 2.1
Name: Sveve
Version: 1.1.0
Summary: A (limited) Python wrapper for Sveve's SMS sending API
Author-email: Alex Simpson <alex.simpson@funbit.no>
Project-URL: repository, https://github.com/alexalligator/sveve
Classifier: Programming Language :: Python :: 3
Classifier: License :: OSI Approved :: MIT License
Classifier: Operating System :: OS Independent
License-File: LICENSE
Requires-Dist: requests >=2
Requires-Dist: pydantic >=2
